vnpy_webtrader/__init__.py
vnpy_webtrader/engine.py
vnpy_webtrader/web.py
vnpy_webtrader/static/__init__.py
vnpy_webtrader/static/index.html
vnpy_webtrader/ui/__init__.py
vnpy_webtrader/ui/web.ico
vnpy_webtrader/ui/widget.py
vnpy_webtrader-1.1.0.dist-info/METADATA
vnpy_webtrader-1.1.0.dist-info/WHEEL
vnpy_webtrader-1.1.0.dist-info/licenses/LICENSE
vnpy_webtrader-1.1.0.dist-info/RECORD
