Metadata-Version: 2.4
Name: vnpy_webtrader
Version: 1.1.0
Summary: Web trader application for VeighNa quant trading framework.
Project-URL: Homepage, https://www.vnpy.com
Project-URL: Documentation, https://www.vnpy.com/docs
Project-URL: Changes, https://github.com/vnpy/vnpy_webtrader/blob/master/CHANGELOG.md
Project-URL: Source, https://github.com/vnpy/vnpy_webtrader/
Project-URL: Forum, https://www.vnpy.com/forum
Author-email: Xiaoyou Chen <xiaoyou.chen@mail.vnpy.com>
License: MIT
License-File: LICENSE
Keywords: algotrading,investment,quant,quantitative,trading
Classifier: Development Status :: 5 - Production/Stable
Classifier: License :: OSI Approved :: MIT License
Classifier: Natural Language :: Chinese (Simplified)
Classifier: Operating System :: OS Independent
Classifier: Programming Language :: Python :: 3
Classifier: Programming Language :: Python :: 3.10
Classifier: Programming Language :: Python :: 3.11
Classifier: Programming Language :: Python :: 3.12
Classifier: Programming Language :: Python :: 3.13
Classifier: Programming Language :: Python :: Implementation :: CPython
Classifier: Topic :: Office/Business :: Financial :: Investment
Classifier: Typing :: Typed
Requires-Python: >=3.10
Requires-Dist: fastapi>=0.115.12
Requires-Dist: passlib>=1.7.4
Requires-Dist: pydantic>=1.0.1
Requires-Dist: python-jose>=3.4.0
Requires-Dist: python-multipart>=0.0.20
Requires-Dist: uvicorn>=0.34.2
Requires-Dist: vnpy>=4.0.0
Requires-Dist: websockets>=15.0.1
